nd_kafka/__init__.py
nd_kafka/base.py
nd_kafka/consumer.py
nd_kafka/producer.py
nd_kafka-0.5.26.dist-info/LICENSE.txt
nd_kafka-0.5.26.dist-info/METADATA
nd_kafka-0.5.26.dist-info/WHEEL
nd_kafka-0.5.26.dist-info/top_level.txt
nd_kafka-0.5.26.dist-info/RECORD
