Metadata-Version: 2.1
Name: nd-kafka
Version: 0.5.26
Summary: Package to create Kafka Producer's & Consumer's
Home-page: UNKNOWN
Author: NiTiN DiXiT
Author-email: nitin.dixit@zopper.com
License: UNKNOWN
Platform: UNKNOWN
Classifier: Programming Language :: Python :: 3
Classifier: License :: OSI Approved :: MIT License
Classifier: Operating System :: OS Independent
Requires-Python: >=3.7
License-File: LICENSE.txt
